{
    "variable": [
        {
            "id": "baseUrl",
            "key": "baseUrl",
            "type": "string",
            "name": "string",
            "value": "http:\/\/localhost:8000"
        }
    ],
    "info": {
        "name": "C.U. UFFS",
        "_postman_id": "4d4e3769-3bb2-4492-b151-933a6ee93cc8",
        "description": "",
        "schema": "https:\/\/schema.getpostman.com\/json\/collection\/v2.1.0\/collection.json"
    },
    "item": [
        {
            "name": "Endpoints",
            "description": "",
            "item": [
                {
                    "name": "api\/v0\/user",
                    "request": {
                        "url": {
                            "host": "{{baseUrl}}",
                            "path": "api\/v0\/user",
                            "query": [],
                            "raw": "{{baseUrl}}\/api\/v0\/user"
                        },
                        "method": "GET",
                        "header": [
                            {
                                "key": "Content-Type",
                                "value": "application\/json"
                            },
                            {
                                "key": "Accept",
                                "value": "application\/json"
                            }
                        ],
                        "body": null,
                        "description": "",
                        "auth": {
                            "type": "noauth"
                        }
                    },
                    "response": [
                        {
                            "header": [
                                {
                                    "key": "cache-control",
                                    "value": "no-cache, private"
                                },
                                {
                                    "key": "content-type",
                                    "value": "application\/json"
                                },
                                {
                                    "key": "vary",
                                    "value": "Origin"
                                }
                            ],
                            "code": 401,
                            "body": "{\"message\":\"Unauthenticated.\"}",
                            "name": ""
                        }
                    ]
                },
                {
                    "name": "api\/v0\/user\/iduffs",
                    "request": {
                        "url": {
                            "host": "{{baseUrl}}",
                            "path": "api\/v0\/user\/iduffs",
                            "query": [],
                            "raw": "{{baseUrl}}\/api\/v0\/user\/iduffs"
                        },
                        "method": "PATCH",
                        "header": [
                            {
                                "key": "Content-Type",
                                "value": "application\/json"
                            },
                            {
                                "key": "Accept",
                                "value": "application\/json"
                            }
                        ],
                        "body": null,
                        "description": "",
                        "auth": {
                            "type": "noauth"
                        }
                    },
                    "response": []
                },
                {
                    "name": "api\/v0\/user",
                    "request": {
                        "url": {
                            "host": "{{baseUrl}}",
                            "path": "api\/v0\/user",
                            "query": [],
                            "raw": "{{baseUrl}}\/api\/v0\/user"
                        },
                        "method": "PUT",
                        "header": [
                            {
                                "key": "Content-Type",
                                "value": "application\/json"
                            },
                            {
                                "key": "Accept",
                                "value": "application\/json"
                            }
                        ],
                        "body": null,
                        "description": "",
                        "auth": {
                            "type": "noauth"
                        }
                    },
                    "response": []
                },
                {
                    "name": "api\/v0\/reset-password",
                    "request": {
                        "url": {
                            "host": "{{baseUrl}}",
                            "path": "api\/v0\/reset-password",
                            "query": [],
                            "raw": "{{baseUrl}}\/api\/v0\/reset-password"
                        },
                        "method": "POST",
                        "header": [
                            {
                                "key": "Content-Type",
                                "value": "application\/json"
                            },
                            {
                                "key": "Accept",
                                "value": "application\/json"
                            }
                        ],
                        "body": null,
                        "description": "",
                        "auth": {
                            "type": "noauth"
                        }
                    },
                    "response": []
                },
                {
                    "name": "api\/v0\/entry",
                    "request": {
                        "url": {
                            "host": "{{baseUrl}}",
                            "path": "api\/v0\/entry",
                            "query": [],
                            "raw": "{{baseUrl}}\/api\/v0\/entry"
                        },
                        "method": "GET",
                        "header": [
                            {
                                "key": "Content-Type",
                                "value": "application\/json"
                            },
                            {
                                "key": "Accept",
                                "value": "application\/json"
                            }
                        ],
                        "body": null,
                        "description": "",
                        "auth": {
                            "type": "noauth"
                        }
                    },
                    "response": [
                        {
                            "header": [
                                {
                                    "key": "cache-control",
                                    "value": "no-cache, private"
                                },
                                {
                                    "key": "content-type",
                                    "value": "application\/json"
                                },
                                {
                                    "key": "vary",
                                    "value": "Origin"
                                }
                            ],
                            "code": 401,
                            "body": "{\"message\":\"Unauthenticated.\"}",
                            "name": ""
                        }
                    ]
                },
                {
                    "name": "api\/v0\/ticket",
                    "request": {
                        "url": {
                            "host": "{{baseUrl}}",
                            "path": "api\/v0\/ticket",
                            "query": [],
                            "raw": "{{baseUrl}}\/api\/v0\/ticket"
                        },
                        "method": "GET",
                        "header": [
                            {
                                "key": "Content-Type",
                                "value": "application\/json"
                            },
                            {
                                "key": "Accept",
                                "value": "application\/json"
                            }
                        ],
                        "body": null,
                        "description": "",
                        "auth": {
                            "type": "noauth"
                        }
                    },
                    "response": [
                        {
                            "header": [
                                {
                                    "key": "cache-control",
                                    "value": "no-cache, private"
                                },
                                {
                                    "key": "content-type",
                                    "value": "application\/json"
                                },
                                {
                                    "key": "vary",
                                    "value": "Origin"
                                }
                            ],
                            "code": 401,
                            "body": "{\"message\":\"Unauthenticated.\"}",
                            "name": ""
                        }
                    ]
                },
                {
                    "name": "api\/v0\/ticket\/balance",
                    "request": {
                        "url": {
                            "host": "{{baseUrl}}",
                            "path": "api\/v0\/ticket\/balance",
                            "query": [],
                            "raw": "{{baseUrl}}\/api\/v0\/ticket\/balance"
                        },
                        "method": "GET",
                        "header": [
                            {
                                "key": "Content-Type",
                                "value": "application\/json"
                            },
                            {
                                "key": "Accept",
                                "value": "application\/json"
                            }
                        ],
                        "body": null,
                        "description": "",
                        "auth": {
                            "type": "noauth"
                        }
                    },
                    "response": [
                        {
                            "header": [
                                {
                                    "key": "cache-control",
                                    "value": "no-cache, private"
                                },
                                {
                                    "key": "content-type",
                                    "value": "application\/json"
                                },
                                {
                                    "key": "vary",
                                    "value": "Origin"
                                }
                            ],
                            "code": 401,
                            "body": "{\"message\":\"Unauthenticated.\"}",
                            "name": ""
                        }
                    ]
                },
                {
                    "name": "api\/v0\/user",
                    "request": {
                        "url": {
                            "host": "{{baseUrl}}",
                            "path": "api\/v0\/user",
                            "query": [],
                            "raw": "{{baseUrl}}\/api\/v0\/user"
                        },
                        "method": "PATCH",
                        "header": [
                            {
                                "key": "Content-Type",
                                "value": "application\/json"
                            },
                            {
                                "key": "Accept",
                                "value": "application\/json"
                            }
                        ],
                        "body": null,
                        "description": "",
                        "auth": {
                            "type": "noauth"
                        }
                    },
                    "response": []
                },
                {
                    "name": "api\/v0\/ticket\/visitor",
                    "request": {
                        "url": {
                            "host": "{{baseUrl}}",
                            "path": "api\/v0\/ticket\/visitor",
                            "query": [],
                            "raw": "{{baseUrl}}\/api\/v0\/ticket\/visitor"
                        },
                        "method": "POST",
                        "header": [
                            {
                                "key": "Content-Type",
                                "value": "application\/json"
                            },
                            {
                                "key": "Accept",
                                "value": "application\/json"
                            }
                        ],
                        "body": null,
                        "description": "",
                        "auth": {
                            "type": "noauth"
                        }
                    },
                    "response": []
                },
                {
                    "name": "api\/v0\/ticket\/thrid-party-employee",
                    "request": {
                        "url": {
                            "host": "{{baseUrl}}",
                            "path": "api\/v0\/ticket\/thrid-party-employee",
                            "query": [],
                            "raw": "{{baseUrl}}\/api\/v0\/ticket\/thrid-party-employee"
                        },
                        "method": "POST",
                        "header": [
                            {
                                "key": "Content-Type",
                                "value": "application\/json"
                            },
                            {
                                "key": "Accept",
                                "value": "application\/json"
                            }
                        ],
                        "body": null,
                        "description": "",
                        "auth": {
                            "type": "noauth"
                        }
                    },
                    "response": []
                },
                {
                    "name": "api\/v0\/ticket",
                    "request": {
                        "url": {
                            "host": "{{baseUrl}}",
                            "path": "api\/v0\/ticket",
                            "query": [],
                            "raw": "{{baseUrl}}\/api\/v0\/ticket"
                        },
                        "method": "POST",
                        "header": [
                            {
                                "key": "Content-Type",
                                "value": "application\/json"
                            },
                            {
                                "key": "Accept",
                                "value": "application\/json"
                            }
                        ],
                        "body": null,
                        "description": "",
                        "auth": {
                            "type": "noauth"
                        }
                    },
                    "response": []
                },
                {
                    "name": "api\/v0\/user\/type",
                    "request": {
                        "url": {
                            "host": "{{baseUrl}}",
                            "path": "api\/v0\/user\/type",
                            "query": [],
                            "raw": "{{baseUrl}}\/api\/v0\/user\/type"
                        },
                        "method": "PUT",
                        "header": [
                            {
                                "key": "Content-Type",
                                "value": "application\/json"
                            },
                            {
                                "key": "Accept",
                                "value": "application\/json"
                            }
                        ],
                        "body": null,
                        "description": "",
                        "auth": {
                            "type": "noauth"
                        }
                    },
                    "response": []
                },
                {
                    "name": "api\/v0\/user",
                    "request": {
                        "url": {
                            "host": "{{baseUrl}}",
                            "path": "api\/v0\/user",
                            "query": [],
                            "raw": "{{baseUrl}}\/api\/v0\/user"
                        },
                        "method": "POST",
                        "header": [
                            {
                                "key": "Content-Type",
                                "value": "application\/json"
                            },
                            {
                                "key": "Accept",
                                "value": "application\/json"
                            }
                        ],
                        "body": null,
                        "description": "",
                        "auth": {
                            "type": "noauth"
                        }
                    },
                    "response": []
                },
                {
                    "name": "api\/v0\/forgot-password",
                    "request": {
                        "url": {
                            "host": "{{baseUrl}}",
                            "path": "api\/v0\/forgot-password",
                            "query": [],
                            "raw": "{{baseUrl}}\/api\/v0\/forgot-password"
                        },
                        "method": "POST",
                        "header": [
                            {
                                "key": "Content-Type",
                                "value": "application\/json"
                            },
                            {
                                "key": "Accept",
                                "value": "application\/json"
                            }
                        ],
                        "body": null,
                        "description": "",
                        "auth": {
                            "type": "noauth"
                        }
                    },
                    "response": []
                },
                {
                    "name": "api\/v0\/menu",
                    "request": {
                        "url": {
                            "host": "{{baseUrl}}",
                            "path": "api\/v0\/menu",
                            "query": [],
                            "raw": "{{baseUrl}}\/api\/v0\/menu"
                        },
                        "method": "POST",
                        "header": [
                            {
                                "key": "Content-Type",
                                "value": "application\/json"
                            },
                            {
                                "key": "Accept",
                                "value": "application\/json"
                            }
                        ],
                        "body": null,
                        "description": "",
                        "auth": {
                            "type": "noauth"
                        }
                    },
                    "response": []
                },
                {
                    "name": "api\/v0\/menu\/{date}",
                    "request": {
                        "url": {
                            "host": "{{baseUrl}}",
                            "path": "api\/v0\/menu\/:date",
                            "query": [],
                            "raw": "{{baseUrl}}\/api\/v0\/menu\/:date",
                            "variable": [
                                {
                                    "id": "date",
                                    "key": "date",
                                    "value": "14",
                                    "description": ""
                                }
                            ]
                        },
                        "method": "PATCH",
                        "header": [
                            {
                                "key": "Content-Type",
                                "value": "application\/json"
                            },
                            {
                                "key": "Accept",
                                "value": "application\/json"
                            }
                        ],
                        "body": null,
                        "description": "",
                        "auth": {
                            "type": "noauth"
                        }
                    },
                    "response": []
                },
                {
                    "name": "api\/v0\/menu\/{date}",
                    "request": {
                        "url": {
                            "host": "{{baseUrl}}",
                            "path": "api\/v0\/menu\/:date",
                            "query": [],
                            "raw": "{{baseUrl}}\/api\/v0\/menu\/:date",
                            "variable": [
                                {
                                    "id": "date",
                                    "key": "date",
                                    "value": "2",
                                    "description": ""
                                }
                            ]
                        },
                        "method": "DELETE",
                        "header": [
                            {
                                "key": "Content-Type",
                                "value": "application\/json"
                            },
                            {
                                "key": "Accept",
                                "value": "application\/json"
                            }
                        ],
                        "body": null,
                        "description": "",
                        "auth": {
                            "type": "noauth"
                        }
                    },
                    "response": []
                },
                {
                    "name": "api\/v0\/report\/entry",
                    "request": {
                        "url": {
                            "host": "{{baseUrl}}",
                            "path": "api\/v0\/report\/entry",
                            "query": [],
                            "raw": "{{baseUrl}}\/api\/v0\/report\/entry"
                        },
                        "method": "GET",
                        "header": [
                            {
                                "key": "Content-Type",
                                "value": "application\/json"
                            },
                            {
                                "key": "Accept",
                                "value": "application\/json"
                            }
                        ],
                        "body": null,
                        "description": "",
                        "auth": {
                            "type": "noauth"
                        }
                    },
                    "response": [
                        {
                            "header": [
                                {
                                    "key": "cache-control",
                                    "value": "no-cache, private"
                                },
                                {
                                    "key": "content-type",
                                    "value": "application\/json"
                                },
                                {
                                    "key": "vary",
                                    "value": "Origin"
                                }
                            ],
                            "code": 401,
                            "body": "{\"message\":\"Unauthenticated.\"}",
                            "name": ""
                        }
                    ]
                },
                {
                    "name": "api\/v0\/report\/ticket",
                    "request": {
                        "url": {
                            "host": "{{baseUrl}}",
                            "path": "api\/v0\/report\/ticket",
                            "query": [],
                            "raw": "{{baseUrl}}\/api\/v0\/report\/ticket"
                        },
                        "method": "GET",
                        "header": [
                            {
                                "key": "Content-Type",
                                "value": "application\/json"
                            },
                            {
                                "key": "Accept",
                                "value": "application\/json"
                            }
                        ],
                        "body": null,
                        "description": "",
                        "auth": {
                            "type": "noauth"
                        }
                    },
                    "response": [
                        {
                            "header": [
                                {
                                    "key": "cache-control",
                                    "value": "no-cache, private"
                                },
                                {
                                    "key": "content-type",
                                    "value": "application\/json"
                                },
                                {
                                    "key": "vary",
                                    "value": "Origin"
                                }
                            ],
                            "code": 401,
                            "body": "{\"message\":\"Unauthenticated.\"}",
                            "name": ""
                        }
                    ]
                },
                {
                    "name": "api\/v0\/block",
                    "request": {
                        "url": {
                            "host": "{{baseUrl}}",
                            "path": "api\/v0\/block",
                            "query": [],
                            "raw": "{{baseUrl}}\/api\/v0\/block"
                        },
                        "method": "POST",
                        "header": [
                            {
                                "key": "Content-Type",
                                "value": "application\/json"
                            },
                            {
                                "key": "Accept",
                                "value": "application\/json"
                            }
                        ],
                        "body": null,
                        "description": "",
                        "auth": {
                            "type": "noauth"
                        }
                    },
                    "response": []
                },
                {
                    "name": "api\/v0\/block\/{id}",
                    "request": {
                        "url": {
                            "host": "{{baseUrl}}",
                            "path": "api\/v0\/block\/:id",
                            "query": [],
                            "raw": "{{baseUrl}}\/api\/v0\/block\/:id",
                            "variable": [
                                {
                                    "id": "id",
                                    "key": "id",
                                    "value": "18",
                                    "description": "The ID of the block."
                                }
                            ]
                        },
                        "method": "PATCH",
                        "header": [
                            {
                                "key": "Content-Type",
                                "value": "application\/json"
                            },
                            {
                                "key": "Accept",
                                "value": "application\/json"
                            }
                        ],
                        "body": null,
                        "description": "",
                        "auth": {
                            "type": "noauth"
                        }
                    },
                    "response": []
                },
                {
                    "name": "api\/v0\/room",
                    "request": {
                        "url": {
                            "host": "{{baseUrl}}",
                            "path": "api\/v0\/room",
                            "query": [],
                            "raw": "{{baseUrl}}\/api\/v0\/room"
                        },
                        "method": "POST",
                        "header": [
                            {
                                "key": "Content-Type",
                                "value": "application\/json"
                            },
                            {
                                "key": "Accept",
                                "value": "application\/json"
                            }
                        ],
                        "body": null,
                        "description": "",
                        "auth": {
                            "type": "noauth"
                        }
                    },
                    "response": []
                },
                {
                    "name": "api\/v0\/room\/{id}",
                    "request": {
                        "url": {
                            "host": "{{baseUrl}}",
                            "path": "api\/v0\/room\/:id",
                            "query": [],
                            "raw": "{{baseUrl}}\/api\/v0\/room\/:id",
                            "variable": [
                                {
                                    "id": "id",
                                    "key": "id",
                                    "value": "2",
                                    "description": "The ID of the room."
                                }
                            ]
                        },
                        "method": "PATCH",
                        "header": [
                            {
                                "key": "Content-Type",
                                "value": "application\/json"
                            },
                            {
                                "key": "Accept",
                                "value": "application\/json"
                            }
                        ],
                        "body": null,
                        "description": "",
                        "auth": {
                            "type": "noauth"
                        }
                    },
                    "response": []
                },
                {
                    "name": "api\/v0\/room\/{id}",
                    "request": {
                        "url": {
                            "host": "{{baseUrl}}",
                            "path": "api\/v0\/room\/:id",
                            "query": [],
                            "raw": "{{baseUrl}}\/api\/v0\/room\/:id",
                            "variable": [
                                {
                                    "id": "id",
                                    "key": "id",
                                    "value": "4",
                                    "description": "The ID of the room."
                                }
                            ]
                        },
                        "method": "DELETE",
                        "header": [
                            {
                                "key": "Content-Type",
                                "value": "application\/json"
                            },
                            {
                                "key": "Accept",
                                "value": "application\/json"
                            }
                        ],
                        "body": null,
                        "description": "",
                        "auth": {
                            "type": "noauth"
                        }
                    },
                    "response": []
                },
                {
                    "name": "api\/v0\/ccr",
                    "request": {
                        "url": {
                            "host": "{{baseUrl}}",
                            "path": "api\/v0\/ccr",
                            "query": [],
                            "raw": "{{baseUrl}}\/api\/v0\/ccr"
                        },
                        "method": "GET",
                        "header": [
                            {
                                "key": "Content-Type",
                                "value": "application\/json"
                            },
                            {
                                "key": "Accept",
                                "value": "application\/json"
                            }
                        ],
                        "body": null,
                        "description": "",
                        "auth": {
                            "type": "noauth"
                        }
                    },
                    "response": [
                        {
                            "header": [
                                {
                                    "key": "cache-control",
                                    "value": "no-cache, private"
                                },
                                {
                                    "key": "content-type",
                                    "value": "application\/json"
                                },
                                {
                                    "key": "vary",
                                    "value": "Origin"
                                }
                            ],
                            "code": 401,
                            "body": "{\"message\":\"Unauthenticated.\"}",
                            "name": ""
                        }
                    ]
                },
                {
                    "name": "api\/v0\/room",
                    "request": {
                        "url": {
                            "host": "{{baseUrl}}",
                            "path": "api\/v0\/room",
                            "query": [],
                            "raw": "{{baseUrl}}\/api\/v0\/room"
                        },
                        "method": "GET",
                        "header": [
                            {
                                "key": "Content-Type",
                                "value": "application\/json"
                            },
                            {
                                "key": "Accept",
                                "value": "application\/json"
                            }
                        ],
                        "body": null,
                        "description": "",
                        "auth": {
                            "type": "noauth"
                        }
                    },
                    "response": [
                        {
                            "header": [
                                {
                                    "key": "cache-control",
                                    "value": "no-cache, private"
                                },
                                {
                                    "key": "content-type",
                                    "value": "application\/json"
                                },
                                {
                                    "key": "vary",
                                    "value": "Origin"
                                }
                            ],
                            "code": 401,
                            "body": "{\"message\":\"Unauthenticated.\"}",
                            "name": ""
                        }
                    ]
                },
                {
                    "name": "api\/v0\/block",
                    "request": {
                        "url": {
                            "host": "{{baseUrl}}",
                            "path": "api\/v0\/block",
                            "query": [],
                            "raw": "{{baseUrl}}\/api\/v0\/block"
                        },
                        "method": "GET",
                        "header": [
                            {
                                "key": "Content-Type",
                                "value": "application\/json"
                            },
                            {
                                "key": "Accept",
                                "value": "application\/json"
                            }
                        ],
                        "body": null,
                        "description": "",
                        "auth": {
                            "type": "noauth"
                        }
                    },
                    "response": [
                        {
                            "header": [
                                {
                                    "key": "cache-control",
                                    "value": "no-cache, private"
                                },
                                {
                                    "key": "content-type",
                                    "value": "application\/json"
                                },
                                {
                                    "key": "vary",
                                    "value": "Origin"
                                }
                            ],
                            "code": 401,
                            "body": "{\"message\":\"Unauthenticated.\"}",
                            "name": ""
                        }
                    ]
                },
                {
                    "name": "api\/v0\/reserve",
                    "request": {
                        "url": {
                            "host": "{{baseUrl}}",
                            "path": "api\/v0\/reserve",
                            "query": [],
                            "raw": "{{baseUrl}}\/api\/v0\/reserve"
                        },
                        "method": "POST",
                        "header": [
                            {
                                "key": "Content-Type",
                                "value": "application\/json"
                            },
                            {
                                "key": "Accept",
                                "value": "application\/json"
                            }
                        ],
                        "body": null,
                        "description": "",
                        "auth": {
                            "type": "noauth"
                        }
                    },
                    "response": []
                },
                {
                    "name": "api\/v0\/reserve\/{id}",
                    "request": {
                        "url": {
                            "host": "{{baseUrl}}",
                            "path": "api\/v0\/reserve\/:id",
                            "query": [],
                            "raw": "{{baseUrl}}\/api\/v0\/reserve\/:id",
                            "variable": [
                                {
                                    "id": "id",
                                    "key": "id",
                                    "value": "4",
                                    "description": "The ID of the reserve."
                                }
                            ]
                        },
                        "method": "DELETE",
                        "header": [
                            {
                                "key": "Content-Type",
                                "value": "application\/json"
                            },
                            {
                                "key": "Accept",
                                "value": "application\/json"
                            }
                        ],
                        "body": null,
                        "description": "",
                        "auth": {
                            "type": "noauth"
                        }
                    },
                    "response": []
                },
                {
                    "name": "api\/v0\/reserve",
                    "request": {
                        "url": {
                            "host": "{{baseUrl}}",
                            "path": "api\/v0\/reserve",
                            "query": [],
                            "raw": "{{baseUrl}}\/api\/v0\/reserve"
                        },
                        "method": "GET",
                        "header": [
                            {
                                "key": "Content-Type",
                                "value": "application\/json"
                            },
                            {
                                "key": "Accept",
                                "value": "application\/json"
                            }
                        ],
                        "body": null,
                        "description": "",
                        "auth": {
                            "type": "noauth"
                        }
                    },
                    "response": [
                        {
                            "header": [
                                {
                                    "key": "cache-control",
                                    "value": "no-cache, private"
                                },
                                {
                                    "key": "content-type",
                                    "value": "application\/json"
                                },
                                {
                                    "key": "vary",
                                    "value": "Origin"
                                }
                            ],
                            "code": 401,
                            "body": "{\"message\":\"Unauthenticated.\"}",
                            "name": ""
                        }
                    ]
                },
                {
                    "name": "api\/v0\/reserve\/{id}",
                    "request": {
                        "url": {
                            "host": "{{baseUrl}}",
                            "path": "api\/v0\/reserve\/:id",
                            "query": [],
                            "raw": "{{baseUrl}}\/api\/v0\/reserve\/:id",
                            "variable": [
                                {
                                    "id": "id",
                                    "key": "id",
                                    "value": "2",
                                    "description": "The ID of the reserve."
                                }
                            ]
                        },
                        "method": "GET",
                        "header": [
                            {
                                "key": "Content-Type",
                                "value": "application\/json"
                            },
                            {
                                "key": "Accept",
                                "value": "application\/json"
                            }
                        ],
                        "body": null,
                        "description": "",
                        "auth": {
                            "type": "noauth"
                        }
                    },
                    "response": [
                        {
                            "header": [
                                {
                                    "key": "cache-control",
                                    "value": "no-cache, private"
                                },
                                {
                                    "key": "content-type",
                                    "value": "application\/json"
                                },
                                {
                                    "key": "vary",
                                    "value": "Origin"
                                }
                            ],
                            "code": 401,
                            "body": "{\"message\":\"Unauthenticated.\"}",
                            "name": ""
                        }
                    ]
                },
                {
                    "name": "api\/v0\/reserve\/time\/{begin}\/{end}",
                    "request": {
                        "url": {
                            "host": "{{baseUrl}}",
                            "path": "api\/v0\/reserve\/time\/:begin\/:end",
                            "query": [],
                            "raw": "{{baseUrl}}\/api\/v0\/reserve\/time\/:begin\/:end",
                            "variable": [
                                {
                                    "id": "begin",
                                    "key": "begin",
                                    "value": "sit",
                                    "description": ""
                                },
                                {
                                    "id": "end",
                                    "key": "end",
                                    "value": "veritatis",
                                    "description": ""
                                }
                            ]
                        },
                        "method": "GET",
                        "header": [
                            {
                                "key": "Content-Type",
                                "value": "application\/json"
                            },
                            {
                                "key": "Accept",
                                "value": "application\/json"
                            }
                        ],
                        "body": null,
                        "description": "",
                        "auth": {
                            "type": "noauth"
                        }
                    },
                    "response": [
                        {
                            "header": [
                                {
                                    "key": "cache-control",
                                    "value": "no-cache, private"
                                },
                                {
                                    "key": "content-type",
                                    "value": "application\/json"
                                },
                                {
                                    "key": "vary",
                                    "value": "Origin"
                                }
                            ],
                            "code": 401,
                            "body": "{\"message\":\"Unauthenticated.\"}",
                            "name": ""
                        }
                    ]
                },
                {
                    "name": "api\/v0\/request\/{id}",
                    "request": {
                        "url": {
                            "host": "{{baseUrl}}",
                            "path": "api\/v0\/request\/:id",
                            "query": [],
                            "raw": "{{baseUrl}}\/api\/v0\/request\/:id",
                            "variable": [
                                {
                                    "id": "id",
                                    "key": "id",
                                    "value": "est",
                                    "description": "The ID of the request."
                                }
                            ]
                        },
                        "method": "PATCH",
                        "header": [
                            {
                                "key": "Content-Type",
                                "value": "application\/json"
                            },
                            {
                                "key": "Accept",
                                "value": "application\/json"
                            }
                        ],
                        "body": null,
                        "description": "",
                        "auth": {
                            "type": "noauth"
                        }
                    },
                    "response": []
                },
                {
                    "name": "api\/v0\/request",
                    "request": {
                        "url": {
                            "host": "{{baseUrl}}",
                            "path": "api\/v0\/request",
                            "query": [],
                            "raw": "{{baseUrl}}\/api\/v0\/request"
                        },
                        "method": "GET",
                        "header": [
                            {
                                "key": "Content-Type",
                                "value": "application\/json"
                            },
                            {
                                "key": "Accept",
                                "value": "application\/json"
                            }
                        ],
                        "body": null,
                        "description": "",
                        "auth": {
                            "type": "noauth"
                        }
                    },
                    "response": [
                        {
                            "header": [
                                {
                                    "key": "cache-control",
                                    "value": "no-cache, private"
                                },
                                {
                                    "key": "content-type",
                                    "value": "application\/json"
                                },
                                {
                                    "key": "vary",
                                    "value": "Origin"
                                }
                            ],
                            "code": 401,
                            "body": "{\"message\":\"Unauthenticated.\"}",
                            "name": ""
                        }
                    ]
                },
                {
                    "name": "api\/v0\/entry\/{enrollment_id}",
                    "request": {
                        "url": {
                            "host": "{{baseUrl}}",
                            "path": "api\/v0\/entry\/:enrollment_id",
                            "query": [],
                            "raw": "{{baseUrl}}\/api\/v0\/entry\/:enrollment_id",
                            "variable": [
                                {
                                    "id": "enrollment_id",
                                    "key": "enrollment_id",
                                    "value": "13",
                                    "description": "The ID of the enrollment."
                                }
                            ]
                        },
                        "method": "POST",
                        "header": [
                            {
                                "key": "Content-Type",
                                "value": "application\/json"
                            },
                            {
                                "key": "Accept",
                                "value": "application\/json"
                            }
                        ],
                        "body": null,
                        "description": "",
                        "auth": {
                            "type": "noauth"
                        }
                    },
                    "response": []
                },
                {
                    "name": "api\/v0\/login",
                    "request": {
                        "url": {
                            "host": "{{baseUrl}}",
                            "path": "api\/v0\/login",
                            "query": [],
                            "raw": "{{baseUrl}}\/api\/v0\/login"
                        },
                        "method": "POST",
                        "header": [
                            {
                                "key": "Content-Type",
                                "value": "application\/json"
                            },
                            {
                                "key": "Accept",
                                "value": "application\/json"
                            }
                        ],
                        "body": null,
                        "description": "",
                        "auth": {
                            "type": "noauth"
                        }
                    },
                    "response": []
                },
                {
                    "name": "api\/v0\/user\/iduffs",
                    "request": {
                        "url": {
                            "host": "{{baseUrl}}",
                            "path": "api\/v0\/user\/iduffs",
                            "query": [],
                            "raw": "{{baseUrl}}\/api\/v0\/user\/iduffs"
                        },
                        "method": "POST",
                        "header": [
                            {
                                "key": "Content-Type",
                                "value": "application\/json"
                            },
                            {
                                "key": "Accept",
                                "value": "application\/json"
                            }
                        ],
                        "body": null,
                        "description": "",
                        "auth": {
                            "type": "noauth"
                        }
                    },
                    "response": []
                },
                {
                    "name": "api\/v0\/user\/operation\/{uid}",
                    "request": {
                        "url": {
                            "host": "{{baseUrl}}",
                            "path": "api\/v0\/user\/operation\/:uid",
                            "query": [],
                            "raw": "{{baseUrl}}\/api\/v0\/user\/operation\/:uid",
                            "variable": [
                                {
                                    "id": "uid",
                                    "key": "uid",
                                    "value": "1",
                                    "description": ""
                                }
                            ]
                        },
                        "method": "GET",
                        "header": [
                            {
                                "key": "Content-Type",
                                "value": "application\/json"
                            },
                            {
                                "key": "Accept",
                                "value": "application\/json"
                            }
                        ],
                        "body": null,
                        "description": "",
                        "auth": {
                            "type": "noauth"
                        }
                    },
                    "response": [
                        {
                            "header": [
                                {
                                    "key": "cache-control",
                                    "value": "no-cache, private"
                                },
                                {
                                    "key": "x-ratelimit-limit",
                                    "value": "60"
                                },
                                {
                                    "key": "x-ratelimit-remaining",
                                    "value": "59"
                                },
                                {
                                    "key": "vary",
                                    "value": "Origin"
                                }
                            ],
                            "code": 204,
                            "body": "",
                            "name": ""
                        }
                    ]
                },
                {
                    "name": "api\/v0\/menu",
                    "request": {
                        "url": {
                            "host": "{{baseUrl}}",
                            "path": "api\/v0\/menu",
                            "query": [],
                            "raw": "{{baseUrl}}\/api\/v0\/menu"
                        },
                        "method": "GET",
                        "header": [
                            {
                                "key": "Content-Type",
                                "value": "application\/json"
                            },
                            {
                                "key": "Accept",
                                "value": "application\/json"
                            }
                        ],
                        "body": null,
                        "description": "",
                        "auth": {
                            "type": "noauth"
                        }
                    },
                    "response": [
                        {
                            "header": [
                                {
                                    "key": "cache-control",
                                    "value": "no-cache, private"
                                },
                                {
                                    "key": "content-type",
                                    "value": "application\/json"
                                },
                                {
                                    "key": "x-ratelimit-limit",
                                    "value": "60"
                                },
                                {
                                    "key": "x-ratelimit-remaining",
                                    "value": "58"
                                },
                                {
                                    "key": "vary",
                                    "value": "Origin"
                                }
                            ],
                            "code": 200,
                            "body": "{\"success\":true,\"data\":{\"current_page\":1,\"data\":[],\"first_page_url\":\"http:\\\/\\\/localhost:8000\\\/api\\\/v0\\\/menu?page=1\",\"from\":null,\"next_page_url\":null,\"path\":\"http:\\\/\\\/localhost:8000\\\/api\\\/v0\\\/menu\",\"per_page\":15,\"prev_page_url\":null,\"to\":null},\"messages\":null}",
                            "name": ""
                        }
                    ]
                }
            ]
        }
    ],
    "auth": {
        "type": "noauth"
    }
}